octopy_graph/__init__.py
octopy_graph/__main__.py
octopy_graph/graph.py
octopy_graph/query.py
octopy_graph-0.1.dist-info/METADATA
octopy_graph-0.1.dist-info/WHEEL
octopy_graph-0.1.dist-info/entry_points.txt
octopy_graph-0.1.dist-info/top_level.txt
octopy_graph-0.1.dist-info/RECORD
