Metadata-Version: 2.1
Name: octopy-graph
Version: 0.1
Summary: A tool for graphing data from the Octopus Energy API
Home-page: https://gitlab.com/broster/octopy-graph
Author: Samuel Broster
Author-email: s.h.broster@gmail.com
License: MIT
Keywords: Octopus Energy,plotly,graph
Platform: UNKNOWN
Classifier: Development Status :: 4 - Beta
Classifier: Intended Audience :: Developers
Classifier: Topic :: Software Development :: Build Tools
Classifier: License :: OSI Approved :: MIT License
Classifier: Programming Language :: Python :: 3.7
Requires-Dist: plotly
Requires-Dist: octopy-api
Requires-Dist: numpy
